quackamollie/core/__init__.py
quackamollie/core/constants.py
quackamollie/core/defaults.py
quackamollie/core/quackamollie.py
quackamollie/core/bot/__init__.py
quackamollie/core/bot/bot_info.py
quackamollie/core/bot/quackamollie_bot.py
quackamollie/core/bot/callback/__init__.py
quackamollie/core/bot/callback/app_settings_callback.py
quackamollie/core/bot/callback/chat_settings_callback.py
quackamollie/core/bot/callback/info_callback.py
quackamollie/core/bot/callback/user_settings_callback.py
quackamollie/core/bot/command/__init__.py
quackamollie/core/bot/command/history.py
quackamollie/core/bot/command/message_by_id.py
quackamollie/core/bot/command/reset.py
quackamollie/core/bot/command/settings_bot_command.py
quackamollie/core/bot/command/start_bot_command.py
quackamollie/core/bot/decorator/__init__.py
quackamollie/core/bot/decorator/acknowledge_with_reactions.py
quackamollie/core/bot/decorator/permissions.py
quackamollie/core/bot/decorator/user_chat_registered.py
quackamollie/core/bot/handler/__init__.py
quackamollie/core/bot/handler/messages.py
quackamollie/core/bot/menu/__init__.py
quackamollie/core/bot/menu/settings_menu.py
quackamollie/core/bot/middleware/__init__.py
quackamollie/core/bot/middleware/user_filter.py
quackamollie/core/bot/utils/__init__.py
quackamollie/core/bot/utils/bot_utils.py
quackamollie/core/cli/__init__.py
quackamollie/core/cli/settings.py
quackamollie/core/cli/command/__init__.py
quackamollie/core/cli/command/alembic_cli_command.py
quackamollie/core/cli/command/db_cli_command.py
quackamollie/core/cli/command/serve_cli_command.py
quackamollie/core/cli/helpers/__init__.py
quackamollie/core/cli/helpers/db_url_config.py
quackamollie/core/cli/helpers/entry_point_command.py
quackamollie/core/cli/helpers/logging.py
quackamollie/core/database/__init__.py
quackamollie/core/database/meta.py
quackamollie/core/database/model/__init__.py
quackamollie/core/database/model/quackamollie_schema.py
quackamollie_core-0.1.dist-info/LICENSE
quackamollie_core-0.1.dist-info/METADATA
quackamollie_core-0.1.dist-info/WHEEL
quackamollie_core-0.1.dist-info/entry_points.txt
quackamollie_core-0.1.dist-info/top_level.txt
quackamollie_core-0.1.dist-info/RECORD
