Metadata-Version: 2.1
Name: quackamollie-core
Version: 0.1
Summary: Core component of the Quackamollie Telegram chat bot
Author-email: QuactorAI <quacktorai@gmail.com>
License: MIT License
Project-URL: Homepage, https://gitlab.com/forge_of_absurd_ducks/quackamollie/lib/quackamollie_core
Keywords: telegram,bot,aiogram,llamaindex,ollama,llmsherpa
Classifier: License :: OSI Approved :: MIT License
Classifier: Programming Language :: Python
Classifier: Programming Language :: Python :: 3 :: Only
Classifier: Programming Language :: Python :: 3.10
Requires-Python: >=3.10
License-File: LICENSE
Requires-Dist: aiogram
Requires-Dist: alembic
Requires-Dist: alembic-postgresql-enum
Requires-Dist: asyncpg
Requires-Dist: click
Requires-Dist: coloredlogs
Requires-Dist: pyfiglet
Requires-Dist: pyyaml
Requires-Dist: sqlalchemy[asyncio]
Provides-Extra: doc
Requires-Dist: sphinx; extra == "doc"
Requires-Dist: sphinx-click; extra == "doc"
Provides-Extra: lint
Requires-Dist: check-manifest; extra == "lint"
Requires-Dist: flake8; extra == "lint"
Requires-Dist: readme-renderer; extra == "lint"
Requires-Dist: safety; extra == "lint"
Requires-Dist: setuptools; extra == "lint"
Requires-Dist: twine; extra == "lint"
Requires-Dist: wheel; extra == "lint"
Provides-Extra: test
Requires-Dist: coverage; extra == "test"
Requires-Dist: pytest; extra == "test"
Requires-Dist: pytest-cov; extra == "test"
Requires-Dist: pytest-xdist; extra == "test"
Requires-Dist: tox; extra == "test"
